timespacex/__init__.py
timespacex/analyzer.py
timespacex/cli.py
timespacex-0.1.0.dist-info/LICENSE
timespacex-0.1.0.dist-info/METADATA
timespacex-0.1.0.dist-info/WHEEL
timespacex-0.1.0.dist-info/entry_points.txt
timespacex-0.1.0.dist-info/top_level.txt
timespacex-0.1.0.dist-info/RECORD
