Metadata-Version: 2.1
Name: timespacex
Version: 0.1.0
Summary: A Python Time and Space Complexity Analyzer
Home-page: https://github.com/hamedyaghoobian/timespacex
Author: Hamed Yaghoobian
Author-email: hamedyaghoobian@gmail.com
Project-URL: Bug Reports, https://github.com/hamedyaghoobian/timespacex/issues
Project-URL: Source, https://github.com/hamedyaghoobian/timespacex
Keywords: complexity analysis,big o notation,algorithm analysis,time complexity,space complexity
Classifier: Development Status :: 4 - Beta
Classifier: Intended Audience :: Developers
Classifier: Topic :: Software Development :: Libraries :: Python Modules
Classifier: Topic :: Software Development :: Testing
Classifier: Topic :: Education
Classifier: License :: OSI Approved :: MIT License
Classifier: Programming Language :: Python :: 3
Classifier: Programming Language :: Python :: 3.6
Classifier: Programming Language :: Python :: 3.7
Classifier: Programming Language :: Python :: 3.8
Classifier: Programming Language :: Python :: 3.9
Classifier: Programming Language :: Python :: 3.10
Classifier: Programming Language :: Python :: 3.11
Requires-Python: >=3.6
License-File: LICENSE
Requires-Dist: rich>=10.0.0
